SimpleQAgent/__init__.py
SimpleQAgent/agents/__init__.py
SimpleQAgent/agents/base_agent.py
SimpleQAgent/agents/q_agent.py
SimpleQAgent/memory/__init__.py
SimpleQAgent/memory/replay_memory.py
SimpleQAgent/networks/__init__.py
SimpleQAgent/networks/deep_q_network.py
SimpleQAgent/networks/networks.py
SimpleQAgents-1.0.5.dist-info/LICENSE
SimpleQAgents-1.0.5.dist-info/METADATA
SimpleQAgents-1.0.5.dist-info/WHEEL
SimpleQAgents-1.0.5.dist-info/top_level.txt
SimpleQAgents-1.0.5.dist-info/RECORD
